ctypes_unicode_proclaunch.py
ctypes_unicode_proclaunch-0.1.0a0.dist-info/licenses/LICENSE
ctypes_unicode_proclaunch-0.1.0a0.dist-info/METADATA
ctypes_unicode_proclaunch-0.1.0a0.dist-info/WHEEL
ctypes_unicode_proclaunch-0.1.0a0.dist-info/top_level.txt
ctypes_unicode_proclaunch-0.1.0a0.dist-info/RECORD
