Metadata-Version: 2.4
Name: ctypes-unicode-proclaunch
Version: 0.1.0a0
Summary: A minimal, robust, and Unicode-aware process launching library using ctypes.
Author-email: Jifeng Wu <jifengwu2k@gmail.com>
License-Expression: MIT
Project-URL: Homepage, https://github.com/jifengwu2k/ctypes-unicode-proclaunch
Project-URL: Bug Tracker, https://github.com/jifengwu2k/ctypes-unicode-proclaunch/issues
Classifier: Programming Language :: Python :: 2
Classifier: Programming Language :: Python :: 3
Classifier: Operating System :: OS Independent
Requires-Python: >=2
License-File: LICENSE
Requires-Dist: escape-nt-command-line-argument
Requires-Dist: find-unicode-executable
Requires-Dist: posix-or-nt
Requires-Dist: read-unicode-environment-variables-dictionary
Requires-Dist: send-recv-json
Requires-Dist: typing; python_version < "3.5"
Dynamic: license-file
